mongodb_helper/__init__.py
mongodb_helper/errors.py
mongodb_helper/helper.py
mongodb_helper-0.13.dist-info/LICENSE
mongodb_helper-0.13.dist-info/METADATA
mongodb_helper-0.13.dist-info/WHEEL
mongodb_helper-0.13.dist-info/top_level.txt
mongodb_helper-0.13.dist-info/RECORD
