Metadata-Version: 2.1
Name: mongodb-helper
Version: 0.13
Summary: Methods that simplify MongoDB collection reading and writing.
Home-page: https://github.com/FlamptX/mongodb-helper
Author: Flampt
License: UNKNOWN
Keywords: mongodb,helper,mongodbhelper
Platform: UNKNOWN
Classifier: Programming Language :: Python :: 3
Classifier: License :: OSI Approved :: MIT License
Classifier: Operating System :: OS Independent
Requires-Python: >=3.6
License-File: LICENSE
Requires-Dist: pymongo
